photobridge/__init__.py
photobridge/apple_scripts.py
photobridge/cli/__init__.py
photobridge/cli/cli.py
photobridge/core.py
photobridge/helpers.py
photobridge-0.1.1.dist-info/LICENSE
photobridge-0.1.1.dist-info/METADATA
photobridge-0.1.1.dist-info/WHEEL
photobridge-0.1.1.dist-info/entry_points.txt
photobridge-0.1.1.dist-info/RECORD
