Metadata-Version: 2.1
Name: photobridge
Version: 0.1.1
Summary: Export photos from a local folder to Apple Photos.
Home-page: https://github.com/keithvassallomt/photobridge
License: GPL-3.0-or-later
Keywords: sync,photo sync,cloud photos
Author: Keith Vassallo
Author-email: keith@vassallo.cloud
Requires-Python: >=3.13,<4.0
Classifier: Development Status :: 5 - Production/Stable
Classifier: Environment :: MacOS X
Classifier: Intended Audience :: End Users/Desktop
Classifier: License :: OSI Approved :: GNU General Public License v3 or later (GPLv3+)
Classifier: Natural Language :: English
Classifier: Operating System :: MacOS
Classifier: Programming Language :: Python
Classifier: Programming Language :: Python :: 3
Classifier: Programming Language :: Python :: Implementation :: CPython
Classifier: Topic :: Utilities
Project-URL: Repository, https://github.com/keithvassallomt/photobridge
